flask_uploads.py
Flask_Uploads_WCL-0.2.1.dist-info/LICENSE
Flask_Uploads_WCL-0.2.1.dist-info/METADATA
Flask_Uploads_WCL-0.2.1.dist-info/WHEEL
Flask_Uploads_WCL-0.2.1.dist-info/top_level.txt
Flask_Uploads_WCL-0.2.1.dist-info/RECORD
