Metadata-Version: 2.1
Name: Flask-Uploads-WCL
Version: 0.2.1
Summary: Flexible and efficient upload handling for Flask
Home-page: https://github.com/maxcountryman/flask-uploads
Author: Matthew "LeafStorm" Frazier
Author-email: leafstormrush@gmail.com
License: MIT
Platform: any
Classifier: Development Status :: 4 - Beta
Classifier: Environment :: Web Environment
Classifier: Intended Audience :: Developers
Classifier: License :: OSI Approved :: MIT License
Classifier: Operating System :: OS Independent
Classifier: Programming Language :: Python
Classifier: Topic :: Internet :: WWW/HTTP :: Dynamic Content
Classifier: Topic :: Software Development :: Libraries :: Python Modules
License-File: LICENSE
Requires-Dist: Flask (>=0.8.0)
